{"type":"FeatureCollection","crs":{"type":"name","properties":{"name":"EPSG:4326"}},"features":[{"type":"Feature","geometry":{"type":"Point","coordinates":[24.903747033573772,60.260041471796065]},"properties":{"name":"Epidemic"}},{"type":"Feature","geometry":{"type":"Point","coordinates":[24.8880249,60.272177639999995]},"properties":{"name":"Epidemic"}},{"type":"Feature","geometry":{"type":"Point","coordinates":[24.932108005474213,60.21275773077521]},"properties":{"name":"Epidemic"}},{"type":"Feature","geometry":{"type":"Point","coordinates":[24.9321664,60.24694308]},"properties":{"name":"Epidemic"}},{"type":"Feature","geometry":{"type":"Point","coordinates":[24.9321664,60.22170852]},"properties":{"name":"Epidemic"}},{"type":"Feature","geometry":{"type":"Point","coordinates":[24.919971325401946,60.21519707444646]},"properties":{"name":"Epidemic"}}]}