{"type":"FeatureCollection","crs":{"type":"name","properties":{"name":"EPSG:4326"}},"features":[{"type":"Feature","geometry":{"type":"Point","coordinates":[24.957295611921303,62.59407943532109]},"properties":{"name":"joo"}},{"type":"Feature","geometry":{"type":"Point","coordinates":[25.01356444,62.58534828]},"properties":{"name":"joo"}},{"type":"Feature","geometry":{"type":"Point","coordinates":[25.02426948,62.57504764]},"properties":{"name":"joo"}},{"type":"Feature","geometry":{"type":"Point","coordinates":[25.018859655119844,62.624159322712785]},"properties":{"name":"joo"}},{"type":"Feature","geometry":{"type":"Point","coordinates":[24.99215436,62.538995400000005]},"properties":{"name":"joo"}},{"type":"Feature","geometry":{"type":"Point","coordinates":[25.03497452,62.57504764]},"properties":{"name":"joo"}},{"type":"Feature","geometry":{"type":"Point","coordinates":[24.96539176,62.51066864]},"properties":{"name":"joo"}},{"type":"Feature","geometry":{"type":"Point","coordinates":[25.04032704,62.58277312]},"properties":{"name":"joo"}},{"type":"Feature","geometry":{"type":"Point","coordinates":[24.932623557872926,62.54537638156364]},"properties":{"name":"joo"}},{"type":"Feature","geometry":{"type":"Point","coordinates":[25.14202492,62.52869476]},"properties":{"name":"joo"}},{"type":"Feature","geometry":{"type":"Point","coordinates":[24.973848580021226,62.59372584501371]},"properties":{"name":"joo"}}]}